MANIFEST.in
README.md
setup.cfg
setup.py
training_config/bert_base_dep.jsonnet
training_config/bert_base_span.jsonnet
training_config/bert_ml_conll2009.jsonnet
training_config/bert_ml_dep.jsonnet
training_config/bert_ml_span.jsonnet
training_config/bert_tiny_dep.jsonnet
training_config/bert_tiny_span.jsonnet
training_config/xlm_r_base_span.jsonnet
transformer_srl/__init__.py
transformer_srl/dataset_readers.py
transformer_srl/eval.py
transformer_srl/models.py
transformer_srl/predictors.py
transformer_srl/utils.py
transformer_srl.egg-info/PKG-INFO
transformer_srl.egg-info/SOURCES.txt
transformer_srl.egg-info/dependency_links.txt
transformer_srl.egg-info/requires.txt
transformer_srl.egg-info/top_level.txt
transformer_srl/resources/eval09.pl
transformer_srl/resources/framelist.txt
transformer_srl/resources/rolelist.txt