Metadata-Version: 2.1
Name: transformer-srl
Version: 2.5
Summary: SRL Transformer model
Home-page: https://github.com/Riccorl/transformer-srl
Author: Riccardo Orlando
Author-email: orlandoricc@gmail.com
License: UNKNOWN
Platform: UNKNOWN
Classifier: Programming Language :: Python :: 3
Classifier: License :: OSI Approved :: MIT License
Classifier: Operating System :: OS Independent
Requires-Python: >=3.6
